demo_car/__init__.py
demo_car/engine.py
demo_car-0.0.1.dist-info/LICENSE
demo_car-0.0.1.dist-info/METADATA
demo_car-0.0.1.dist-info/WHEEL
demo_car-0.0.1.dist-info/top_level.txt
demo_car-0.0.1.dist-info/RECORD
