Metadata-Version: 2.1
Name: demo-car
Version: 0.0.1
Summary: A demo_car package
Home-page: https://github.com/umeshdhakar/sample-python-package
Author: Umesh Kumar Dhakar
Author-email: kumar886umesh@gmail.com
License: UNKNOWN
Platform: UNKNOWN
Classifier: Programming Language :: Python :: 3
Classifier: License :: OSI Approved :: MIT License
Classifier: Operating System :: OS Independent
